platingsoc/__about__.py
platingsoc/__init__.py
platingsoc/plating_id.py
platingsoc-0.0.1.dist-info/METADATA
platingsoc-0.0.1.dist-info/WHEEL
platingsoc-0.0.1.dist-info/licenses/LICENSE.txt
platingsoc-0.0.1.dist-info/RECORD
